{"js.ts_es6_手写promise所有函数.md":"08797755","js.ts_基础_垃圾回收.md":"9f478f5d","js.ts_基础_eventloop.md":"e1a2dc5c","js.ts_基础_一文搞懂map函数.md":"a32280e1","js.ts_基础_new操作符.md":"0276d72c","js.ts_js上下文和执行栈.md":"83cc4f48","js.ts_基础_js中的map和weakmap.md":"0e7a8b5b","开发总结_adobe-pr插件.md":"9617db0b","react_index.md":"73fd1ed0","vue_源码分析_vnode与diff算法.md":"299926c2","vue_组件通信_api-attrs.md":"b86975b4","vue_组件通信_api-props.md":"ca78da2c","vue_组件通信_api-parent.md":"2f0543db","开发总结_github-deploy.md":"ee869367","算法_二叉树_层序遍历.md":"4f8c59cc","vue_组件通信_api-provide.md":"d549d1c4","index.md":"dc092989","js.ts_设计模式_发布订阅模式.md":"cdf568d0","tips_2023.3.5.md":"2f72aeca","开发总结_canvas_canvas.md":"a1b93232","算法_面试算法题_1.15七牛云春招笔试题.md":"598eefbe","算法_面试算法题_1.7字节.md":"89322c7c","计算机基础_index.md":"5135bb83","面试_cz前端_html_css.md":"61e5a875","面试_cz前端_js基础_作用域和闭包.md":"8d1fcffa","面试_cz前端_js基础_原型和原型链.md":"cb074d6b","面试_前端_http_http的优先级.md":"c3303fbc","面试_cz前端_js基础_变量类型和计算.md":"0f30d08d","面试_前端_url到页面_总章.md":"79d7ad6b","面试_前端_事件_事件循环.md":"2ad554a9","面试_前端_事件_事件机制.md":"32e7679e","面试_前端_客户端存储.md":"528a086e","面试_前端_跨域.md":"9a87f6dc","面试_cz前端_js基础_异步.md":"fb2cf0be","面试_前端_flexandgrid.md":"26f33aa4"}
